LICENSE
MANIFEST.in
README.md
setup.py
tests/__init__.py
tests/manage.py
tests/settings.py
tests/urls.py
tests/views.py
url_obfuscate/__init__.py
url_obfuscate/decorators.py
url_obfuscate/helpers.py
url_obfuscate.egg-info/PKG-INFO
url_obfuscate.egg-info/SOURCES.txt
url_obfuscate.egg-info/dependency_links.txt
url_obfuscate.egg-info/requires.txt
url_obfuscate.egg-info/top_level.txt
url_obfuscate/templatetags/__init__.py
url_obfuscate/templatetags/obfuscate.py