Metadata-Version: 1.1
Name: url-obfuscate
Version: 0.1.2
Summary: This is a Django application that provides methods to obfuscate/deobfuscate URLs
Home-page: https://github.com/lmanzurv/url_ofbuscate
Author: Laura Manzur
Author-email: lmanzurv@gmai.com
License: Apache License
Download-URL: https://github.com/lmanzurv/url_ofbuscate
Keywords: django url obfuscate obfuscation
Platform: UNKNOWN
Classifier: Framework :: Django
Classifier: License :: OSI Approved :: Academic Free License (AFL)
Classifier: Natural Language :: English
Classifier: Programming Language :: Python :: 2.7
